hubo/__init__.py
hubo/cs1graphics.py
hubo/cs1media.py
hubo/cs1robots.py
hubo/cs1robots_images.py
hubo-0.0.2.dist-info/LICENSE
hubo-0.0.2.dist-info/METADATA
hubo-0.0.2.dist-info/WHEEL
hubo-0.0.2.dist-info/top_level.txt
hubo-0.0.2.dist-info/RECORD
